cryptomarketdata/__init__.py
cryptomarketdata/auth.py
cryptomarketdata/data_loader.py
cryptomarketdata/utils.py
cryptomd/__init__.py
cryptomd/auth.py
cryptomd/data_loader.py
cryptomd/utils.py
cryptomd-0.2.1.dist-info/licenses/LICENSE
cryptomd-0.2.1.dist-info/METADATA
cryptomd-0.2.1.dist-info/WHEEL
cryptomd-0.2.1.dist-info/top_level.txt
cryptomd-0.2.1.dist-info/RECORD
