Metadata-Version: 2.4
Name: cryptomd
Version: 0.2.1
Summary: Lib for cryptomarket data
Home-page: https://github.com/MuonSevasch/cryptomarketdata
Author: Arseny Zaitsev
Author-email: arseny.zaitsev@gmail.com
Classifier: Programming Language :: Python :: 3
Classifier: License :: OSI Approved :: Apache Software License
Classifier: Operating System :: OS Independent
Requires-Python: >=3.8
License-File: LICENSE
Requires-Dist: requests>=2.25.1
Dynamic: author
Dynamic: author-email
Dynamic: classifier
Dynamic: description
Dynamic: description-content-type
Dynamic: home-page
Dynamic: license-file
Dynamic: requires-dist
Dynamic: requires-python
Dynamic: summary
